Metadata-Version: 1.0
Name: logging-enterprise
Version: 0.2
Summary: Logger enterprise edition
Home-page: UNKNOWN
Author: exp101t
Author-email: nobody@nonexistent.net
License: UNKNOWN
Keywords: logging,enterprise
Platform: UNKNOWN
